README.md
setup.cfg
setup.py
idbiaas/__init__.py
idbiaas/idbiaas.py
idbiaas/idbiaas_test.py
idbiaas.egg-info/PKG-INFO
idbiaas.egg-info/SOURCES.txt
idbiaas.egg-info/dependency_links.txt
idbiaas.egg-info/entry_points.txt
idbiaas.egg-info/requires.txt
idbiaas.egg-info/top_level.txt