Metadata-Version: 1.0
Name: idbiaas
Version: 0.0.5
Summary: IDB IAAS adapter
Home-page: https://github.com/idb-project/idbiaas
Author: bytemine GmbH
Author-email: schuller@bytemine.net
License: UNKNOWN
Platform: UNKNOWN
